{
  "issueId": "5b3b8bb6-594a-4b53-8e69-1ad0212e18bc",
  "title": "Build: A calculator where users input filament weight (g), spool price, and spool weight. It calculates the cost per print and ",
  "slug": "3d-printing-filament-cost-calculator",
  "keywordTarget": "Build: A calculator where users input filament weight (g), spool price, and spool weight. It calculates the cost per print and ",
  "timestamp": "2026-04-16T22:34:07.251Z",
  "sourceIssueUrl": "http://localhost:3100/issues/5b3b8bb6-594a-4b53-8e69-1ad0212e18bc"
}